[
  {
    "title": "Silo (2023)",
    "year": 2023,
    "media": "tv",
    "note": "post-apocalyptic underground society unraveling its own secrets; Puzzle Structure mystery | Science Fiction | Dystopia | Prestige TV",
    "tmdbId": 125988,
    "poster_path": "/gMYZZvnkVNTqSVnVCphWbPXwWwb.jpg",
    "streaming": [
      "Apple TV",
      "Apple TV Amazon Channel"
    ],
    "trailer": "https://www.youtube.com/watch?v=8ZYhuvIv1pA",
    "genres": [
      "Sci-Fi & Fantasy",
      "Drama"
    ],
    "verifiedAt": 1783273729010
  },
  {
    "title": "Star City (2026)",
    "year": 2026,
    "media": "tv",
    "note": "Alt-History Soviet space race from the For All Mankind universe; Political Intrigue behind the Iron Curtain | Science Fiction | Prestige TV",
    "tmdbId": 252107,
    "poster_path": "/aOyhj8ERPpijIyrwJoTd4ZEhqJR.jpg",
    "streaming": [
      "Apple TV",
      "Apple TV Amazon Channel"
    ],
    "trailer": "https://www.youtube.com/watch?v=V-yAMs307W4",
    "genres": [
      "Drama",
      "Sci-Fi & Fantasy",
      "War & Politics"
    ],
    "verifiedAt": 1783273729087
  }
]